{
  "personopplysninger": {
    "fnr": "12345678910",
    "fornavn": "fornavn",
    "mellomnavn": "ØÆÅ",
    "etternavn": "etternavn",
    "telefonnummer": "90011900",
    "gateadresse": "storgata 1",
    "bruksenhet": "20e",
    "postnummer": "0909",
    "poststed": "Oslo",
    "bokommune": "Oslo",
    "statsborgerskap": "Tunisisk",
    "flyktning": true,
    "borFastINorge": true
  },
  "boforhold": {
    "borSammenMed": [
      "Barn over 18"
    ],
    "delerBoligMed": [
      {
        "navn": "Turid Schønberg",
        "fødselsnummer": "12345678910"
      }
    ],
    "delerBolig": true
  },
  "utenlandsopphold": {
    "registrertePerioder": [
      {
        "utreisedato": "31122019",
        "innreisedato": "04012020"
      }
    ],
    "planlagtePerioder": [
      {
        "utreisedato": "01032020",
        "innreisedato": "05032020"
      },
      {
        "utreisedato": "01042020",
        "innreisedato": "05042020"
      }
    ],
    "utenlandsopphold": true,
    "planlagtUtenlandsopphold": true
  },
  "oppholdstillatelse": {
    "harVarigOpphold": false,
    "utløpsDato": "30/10/2024",
    "søktOmForlengelse": false
  },
  "inntektPensjonFormue": {
    "pensjonsOrdning": [
      {
        "ordning": "KLP",
        "beløp": "99"
      },
      {
        "ordning": "SPK",
        "beløp": "98"
      }
    ],
    "framsattKravAnnenYtelse": true,
    "framsattKravAnnenYtelseBegrunnelse": "Hundepensjon",
    "harInntekt": true,
    "inntektBeløp": "2500",
    "harPensjon": true,
    "sumPersoninntekt": "30000",
    "harFormueEiendom": true,
    "formueBeløp": "2323",
    "harFinansFormue": false,
    "harAnnenFormue": true,
    "typeFormue": "hytte i afrika",
    "samletSkattetakst": "3500",
    "harSosialStønad": true
  },
  "forNAV": {
    "målform": "Nynorsk",
    "søkerMøttPersonlig": true,
    "harFullmektigMøtt": true,
    "erPassSjekket": true,
    "forNAVmerknader": "Trivelig type"
  }
}